CHANGELOG.txt
LICENSE.txt
MANIFEST.in
README.txt
setup.cfg
setup.py
FormConvert.egg-info/PKG-INFO
FormConvert.egg-info/SOURCES.txt
FormConvert.egg-info/dependency_links.txt
FormConvert.egg-info/entry_points.txt
FormConvert.egg-info/not-zip-safe
FormConvert.egg-info/requires.txt
FormConvert.egg-info/top_level.txt
doc/index.txt
doc/source/api.rst
doc/source/conf.py
doc/source/index.rst
doc/source/manual.rst
formconvert/__init__.py
test/README.txt
test/doc.py