Metadata-Version: 1.0
Name: FormConvert
Version: 0.2.0
Summary: Tools for working with Forms, including ConversionKit converters to convert HTML values to Python data structures.
Home-page: http://jimmyg.org/work/code/formconvert/index.html
Author: James Gardner
Author-email: UNKNOWN
License: GNU AGPLv3
Platform: UNKNOWN
Classifier: Development Status :: 3 - Alpha
Classifier: Environment :: Web Environment
Classifier: License :: OSI Approved :: GNU Affero General Public License v3
Classifier: Programming Language :: Python
